tasmidi/__init__.py
tasmidi/convert.py
tasmidi/map.py
tasmidi/notes.py
tasmidi/track.py
tasmidi-0.1.1.dist-info/entry_points.txt
tasmidi-0.1.1.dist-info/WHEEL
tasmidi-0.1.1.dist-info/METADATA
tasmidi-0.1.1.dist-info/RECORD
