Metadata-Version: 2.1
Name: tasmidi
Version: 0.1.1
Summary: 
Home-page: https://github.com/markrawls/tasmidi
Author: Mark Rawls
Author-email: markrawls96@gmail.com
Requires-Python: >=3.7,<4.0
Classifier: Programming Language :: Python :: 3
Classifier: Programming Language :: Python :: 3.7
Classifier: Programming Language :: Python :: 3.8
Requires-Dist: mido (>=1.2.9,<2.0.0)
Project-URL: Repository, https://github.com/markrawls/tasmidi
